pramda/__init__.py
pramda/add.py
pramda/add_test.py
pramda/adjust.py
pramda/adjust_test.py
pramda/all.py
pramda/all_pass.py
pramda/all_pass_test.py
pramda/all_test.py
pramda/always.py
pramda/any.py
pramda/any_pass.py
pramda/any_pass_test.py
pramda/any_test.py
pramda/cond.py
pramda/cond_test.py
pramda/curry.py
pramda/dec.py
pramda/filter.py
pramda/filter_test.py
pramda/find.py
pramda/find_test.py
pramda/gt.py
pramda/gt_test.py
pramda/gte.py
pramda/gte_test.py
pramda/inc.py
pramda/is_truthy.py
pramda/lt.py
pramda/lt_test.py
pramda/lte.py
pramda/lte_test.py
pramda/map.py
pramda/map_test.py
pramda/omit.py
pramda/omit_test.py
pramda/pick.py
pramda/pick_test.py
pramda/pipe.py
pramda/pipe_test.py
pramda/reduce.py
pramda/reduce_test.py
pramda-1.4.0.dist-info/LICENSE.txt
pramda-1.4.0.dist-info/METADATA
pramda-1.4.0.dist-info/WHEEL
pramda-1.4.0.dist-info/RECORD
