Metadata-Version: 2.1
Name: pramda
Version: 1.4.0
Summary: Pramda helps you implement functional programming in Python
Home-page: http://github.com/pramda/pramda
License: MIT
Author: myuksal
Author-email: jupyter@kakao.com
Requires-Python: >=3.10,<4.0
Classifier: Development Status :: 5 - Production/Stable
Classifier: License :: OSI Approved :: MIT License
Classifier: Programming Language :: Python :: 3
Classifier: Programming Language :: Python :: 3.10
Classifier: Programming Language :: Python :: 3.11
Classifier: Programming Language :: Python :: 3.12
Classifier: Programming Language :: Python :: 3.13
Project-URL: Repository, http://github.com/pramda/pramda
